gactivity/__init__.py
gactivity/__main__.py
gactivity/activity.py
tests/test_github_activity.py
github_user_activity_cli-1.0.2.dist-info/METADATA
github_user_activity_cli-1.0.2.dist-info/WHEEL
github_user_activity_cli-1.0.2.dist-info/entry_points.txt
github_user_activity_cli-1.0.2.dist-info/top_level.txt
github_user_activity_cli-1.0.2.dist-info/RECORD
