Metadata-Version: 2.4
Name: github-user-activity-cli
Version: 1.0.2
Summary: Simple project for educational purposes
Author-email: elcbi <sebastian.gcruz64@gmail.com>
License-Expression: MIT
Project-URL: Repository, https://github.com/sebastiancruzg/github-activity-cli
Requires-Python: >=3.10
Requires-Dist: aiohttp>=3.11.18
Provides-Extra: dev
Requires-Dist: build; extra == "dev"
Requires-Dist: twine; extra == "dev"
